{
  "candidate_solution_path": "../../ConeHomogeneityLaplaceSolution.md",
  "candidate_path": "ConeHomogeneityLaplaceSolution.md",
  "persona_version": "v2",
  "gate": "pass",
  "would_say_target_line": true,
  "raw_reaction": "天晴れだ　生涯貴様を忘れることはないだろう",
  "reason": "The solution treats the original stopping time exactly, derives P(S_n <= 1) = 1/n! from cone homogeneity plus Laplace normalization rather than assuming simplex volume, and gives a compact distinct argument with no hidden probabilistic jump."
}
